abc_storage/__init__.py
abc_storage/generators/__init__.py
abc_storage/generators/answers.py
abc_storage/generators/primary_key.py
abc_storage/generators/questions.py
abc_storage/generators/users.py
tests/client/__init__.py
tests/client/data.py
tests/client/test_answer.py
tests/client/test_question.py
tests/client/test_user.py
tests/storage/__init__.py
tests/storage/answer/__init__.py
tests/storage/answer/test_.py
tests/storage/answer/test_primary_key.py
tests/storage/quiestion/__init__.py
tests/storage/quiestion/test_.py
tests/storage/quiestion/test_block_type.py
tests/storage/quiestion/test_text.py
tests/storage/quiestion/test_title.py
tests/storage/user/__init__.py
tests/storage/user/test_.py
tests/storage/user/test_active.py
tests/storage/user/test_answers_ids.py
tests/storage/user/test_auth_hash.py
tests/storage/user/test_birth_date.py
tests/storage/user/test_cell_phone.py
tests/storage/user/test_email.py
tests/storage/user/test_first_name.py
tests/storage/user/test_last_name.py
abc_storage-0.1.0.dist-info/METADATA
abc_storage-0.1.0.dist-info/WHEEL
abc_storage-0.1.0.dist-info/entry_points.txt
abc_storage-0.1.0.dist-info/top_level.txt
abc_storage-0.1.0.dist-info/RECORD
