Metadata-Version: 2.1
Name: abc-storage
Version: 0.1.0
Summary: This service implements storage of abc project
Home-page: https://github.com/Hedgehogues/abc-storage
Author: Egor Urvanov
Author-email: hedgehogues@bk.ru
License: UNKNOWN
Platform: UNKNOWN
Classifier: Programming Language :: Python :: 3.7
Classifier: Operating System :: OS Independent
Requires-Dist: loguru (==0.4.1)
Requires-Dist: starlette (==0.13.2)
Requires-Dist: vault-client (==0.3.2)
Requires-Dist: prometheus-client (==0.7.1)
Requires-Dist: flask (==1.1.2)
Requires-Dist: eve (==1.1.1)
Requires-Dist: pytest
Requires-Dist: pytest-asyncio (==0.12.0)
Requires-Dist: eve-healthcheck (==0.3.0)
Requires-Dist: eve-swagger (==0.0.11)
Requires-Dist: flasgger (==0.9.4)
Requires-Dist: flask-cors (==3.0.8)
Requires-Dist: python-clients (==0.12.1)
Requires-Dist: faker
